paquetes/__init__.py
paquetes/cursos.py
taikpo-0.1.0.dist-info/METADATA
taikpo-0.1.0.dist-info/WHEEL
taikpo-0.1.0.dist-info/top_level.txt
taikpo-0.1.0.dist-info/RECORD
