Metadata-Version: 2.4
Name: taikpo
Version: 0.1.0
Summary: Una pruebita, papi.
Home-page: https://ole.com.ar
Author: taielkpo
Dynamic: author
Dynamic: description-content-type
Dynamic: home-page
Dynamic: summary
